celery_heartbeat/__init__.py
celery_heartbeat/apps.py
celery_heartbeat/heartbeat.py
celery_heartbeat/tasks.py
celery_heartbeat/utils.py
django_celery_heartbeat-0.1.0.dist-info/LICENSE.txt
django_celery_heartbeat-0.1.0.dist-info/METADATA
django_celery_heartbeat-0.1.0.dist-info/WHEEL
django_celery_heartbeat-0.1.0.dist-info/top_level.txt
django_celery_heartbeat-0.1.0.dist-info/RECORD
