Metadata-Version: 2.1
Name: django-celery-heartbeat
Version: 0.1.0
Summary: A Django app to provide basic celery health monitoring.
Home-page: https://github.com/octavenz/django-celery-heartbeat
Author: Richard Campen
Author-email: richard@campen.co
License: MIT
Platform: UNKNOWN
Classifier: Environment :: Web Environment
Classifier: Framework :: Django
Classifier: Intended Audience :: Developers
Classifier: License :: OSI Approved :: MIT License
Classifier: Operating System :: OS Independent
Classifier: Programming Language :: Python
Classifier: Topic :: Internet :: WWW/HTTP
Classifier: Topic :: Internet :: WWW/HTTP :: Dynamic Content
